auto_qpf/__init__.py
auto_qpf/enums.py
auto_qpf/generate_chapters.py
auto_qpf/long_path.py
auto_qpf/qpf.py
auto_qpf/qpf_exceptions.py
autoqpf-0.2.5.dist-info/licenses/LICENSE
autoqpf-0.2.5.dist-info/METADATA
autoqpf-0.2.5.dist-info/WHEEL
autoqpf-0.2.5.dist-info/top_level.txt
autoqpf-0.2.5.dist-info/RECORD
