Metadata-Version: 2.4
Name: autoqpf
Version: 0.2.5
Summary: Automated qpf creator and additional utils
Author: jessielw
License: MIT License
Project-URL: Source, https://github.com/jessielw/AutoQPF
Project-URL: Tracker, https://github.com/jessielw/AutoQPF/issues
Keywords: automatic,srt,ogm,x264,x265,chapter,txt,qpf,timecodes,qpfgenerator,framecodes
Classifier: License :: OSI Approved :: MIT License
Classifier: Programming Language :: Python :: 3
Classifier: Programming Language :: Python :: 3 :: Only
Classifier: Programming Language :: Python :: 3.9
Classifier: Programming Language :: Python :: 3.10
Classifier: Programming Language :: Python :: 3.11
Classifier: Programming Language :: Python :: 3.12
Classifier: Programming Language :: Python :: 3.13
Classifier: Topic :: Multimedia :: Video
Classifier: Topic :: Software Development :: Libraries :: Python Modules
Requires-Python: >=3.11
License-File: LICENSE
Requires-Dist: pymediainfo
Dynamic: license-file
